xiaomi_gateway/__init__.py
PyXiaomiGateway-0.14.3.dist-info/METADATA
PyXiaomiGateway-0.14.3.dist-info/WHEEL
PyXiaomiGateway-0.14.3.dist-info/top_level.txt
PyXiaomiGateway-0.14.3.dist-info/RECORD
